mycalc/calculator.py
KIMMINSUuu-0.0.1.dist-info/METADATA
KIMMINSUuu-0.0.1.dist-info/WHEEL
KIMMINSUuu-0.0.1.dist-info/top_level.txt
KIMMINSUuu-0.0.1.dist-info/RECORD
