Metadata-Version: 2.1
Name: KIMMINSUuu
Version: 0.0.1
Summary: my calculator
Home-page: https://github.com/KIMMINSUuu/calc0001
Download-URL: https://github.com/KIMMINSUuu/calc0001/archive/refs/tags/v0.0.1.zip
Author: minsu kim
License: UNKNOWN
Platform: UNKNOWN
Classifier: Programming Language :: Python :: 3
